latent_geometry/__init__.py
latent_geometry/config.py
latent_geometry/data.py
latent_geometry/path.py
latent_geometry/utils.py
latent_geometry/manifold/__init__.py
latent_geometry/manifold/abstract.py
latent_geometry/manifold/latent.py
latent_geometry/mapping/__init__.py
latent_geometry/mapping/abstract.py
latent_geometry/mapping/identity.py
latent_geometry/mapping/torch.py
latent_geometry/mapping/toy.py
latent_geometry/metric/__init__.py
latent_geometry/metric/abstract.py
latent_geometry/metric/connection.py
latent_geometry/metric/euclidean.py
latent_geometry/metric/manifold.py
latent_geometry/metric/pullback.py
latent_geometry/model/__init__.py
latent_geometry/model/mnist_vae.py
latent_geometry/optim/__init__.py
latent_geometry/optim/metric.py
latent_geometry/optim/torch.py
latent_geometry/solver/__init__.py
latent_geometry/solver/abstract.py
latent_geometry/solver/exponential.py
latent_geometry/solver/logarithm.py
latent_geometry/solver/result.py
latent_geometry-1.1.0.dist-info/LICENSE
latent_geometry-1.1.0.dist-info/METADATA
latent_geometry-1.1.0.dist-info/WHEEL
latent_geometry-1.1.0.dist-info/top_level.txt
latent_geometry-1.1.0.dist-info/RECORD
