Metadata-Version: 2.1
Name: latent-geometry
Version: 1.1.0
Summary: Python package allowing for the exploration of latent spaces of generative models through Riemannian geometry.
Author: Michal Kucharczyk
Author-email: kucharczi@gmail.com
License: GPLv3
Classifier: Development Status :: 4 - Beta
Classifier: License :: OSI Approved :: GNU General Public License v3 (GPLv3)
Classifier: Programming Language :: Python :: 3.9
Classifier: Programming Language :: Python :: 3.10
Classifier: Topic :: Scientific/Engineering
Classifier: Topic :: Software Development :: Libraries
Requires-Python: >=3.9
License-File: LICENSE
Requires-Dist: torch (>=2.0.0)
Requires-Dist: numpy (>=1.22.0)
Requires-Dist: scipy (>=1.10.1)
Requires-Dist: torchvision
Provides-Extra: data
Requires-Dist: ipykernel ; extra == 'data'
Requires-Dist: matplotlib ; extra == 'data'
Requires-Dist: dvc[gdrive] ; extra == 'data'
Requires-Dist: pandas ; extra == 'data'
Requires-Dist: plotly ; extra == 'data'
Requires-Dist: clearml ; extra == 'data'
Requires-Dist: nbconvert ; extra == 'data'
Provides-Extra: dev
Requires-Dist: black[jupyter] (~=22.3.0) ; extra == 'dev'
Requires-Dist: flake8 ; extra == 'dev'
Requires-Dist: isort ; extra == 'dev'
Requires-Dist: mypy ; extra == 'dev'
Requires-Dist: pre-commit ; extra == 'dev'
Requires-Dist: pytest ; extra == 'dev'
Requires-Dist: twine ; extra == 'dev'
Requires-Dist: build ; extra == 'dev'
Provides-Extra: test
Requires-Dist: pytest ; extra == 'test'
Requires-Dist: mypy ; extra == 'test'
